zsx_Hic_plot.py
zsx_Hic_plot-2.1.0.dist-info/METADATA
zsx_Hic_plot-2.1.0.dist-info/WHEEL
zsx_Hic_plot-2.1.0.dist-info/top_level.txt
zsx_Hic_plot-2.1.0.dist-info/RECORD
