Metadata-Version: 2.1
Name: zsx_Hic_plot
Version: 2.1.0
Summary: Facile & flexible heatmap plotting
Author-email: Zhang Senxin <sxzhang997@qq.com>
Project-URL: Homepage, https://github.com/ZhangSenxin/plot_packages
Project-URL: Bug Tracker, https://github.com/ZhangSenxin/plot_packages/issues
Classifier: Programming Language :: Python :: 3
Classifier: License :: OSI Approved :: MIT License
Classifier: Operating System :: OS Independent
Requires-Python: >=3.6
Requires-Dist: zsx-some-tools >=2.0.0
Requires-Dist: zsx-facile-heatmap
Requires-Dist: zsx-color-bar
Requires-Dist: zsx-HMM
